Compiled from "GenericMechanism.java"
public class com.example.review.polymorphic.generic.GenericMechanism {
  public com.example.review.polymorphic.generic.GenericMechanism();
    Code:
       0: aload_0
       1: invokespecial #1                  // Method java/lang/Object."<init>":()V
       4: return

  public static void main(java.lang.String[]);
    Code:
       0: new           #2                  // class com/example/review/polymorphic/generic/GenericMechanism$Holder
       3: dup
       4: aconst_null
       5: invokespecial #3                  // Method com/example/review/polymorphic/generic/GenericMechanism$Holder."<init>":(Lcom/example/review/polymorphic/generic/GenericMechanism$1;)V
       8: astore_1
       9: aload_1
      10: bipush        10
      12: invokestatic  #4                  // Method java/lang/Integer.valueOf:(I)Ljava/lang/Integer;
      15: invokevirtual #5                  // Method com/example/review/polymorphic/generic/GenericMechanism$Holder.set:(Ljava/lang/Object;)V
      18: aload_1
      19: invokevirtual #6                  // Method com/example/review/polymorphic/generic/GenericMechanism$Holder.get:()Ljava/lang/Object;
      22: checkcast     #7                  // class java/lang/Integer
      25: astore_2
      26: return
}
